conbuddy/__init__.py
conbuddy/main.py
conbuddy-0.1.1a0.dist-info/LICENSE
conbuddy-0.1.1a0.dist-info/WHEEL
conbuddy-0.1.1a0.dist-info/METADATA
conbuddy-0.1.1a0.dist-info/RECORD
